LICENSE
MANIFEST.in
README.rst
setup.cfg
setup.py
django_payline_dotir.egg-info/PKG-INFO
django_payline_dotir.egg-info/SOURCES.txt
django_payline_dotir.egg-info/dependency_links.txt
django_payline_dotir.egg-info/not-zip-safe
django_payline_dotir.egg-info/requires.txt
django_payline_dotir.egg-info/top_level.txt
example/README.rst
example/payline_ir/manage.py
example/payline_ir/requirements.txt
example/payline_ir/payline_ir/__init__.py
example/payline_ir/payline_ir/settings.py
example/payline_ir/payline_ir/tests.py
example/payline_ir/payline_ir/urls.py
example/payline_ir/payline_ir/views.py
example/payline_ir/payline_ir/wsgi.py
example/payline_ir/payline_ir/templates/pay_form.html
example/payline_ir/payline_ir/templates/successful_payment.html
payline_dotir/__init__.py
payline_dotir/payment_gateway.py
payline_dotir/settings.py
payline_dotir/ulrs.py
payline_dotir/views.py